torch_module_cache/__init__.py
torch_module_cache/decorator.py
torch_module_cache/utils/__init__.py
torch_module_cache/utils/cache_utils.py
torch_module_cache-0.1.4.dist-info/licenses/LICENSE
torch_module_cache-0.1.4.dist-info/METADATA
torch_module_cache-0.1.4.dist-info/WHEEL
torch_module_cache-0.1.4.dist-info/top_level.txt
torch_module_cache-0.1.4.dist-info/RECORD
