Metadata-Version: 2.4
Name: torch-module-cache
Version: 0.1.4
Summary: A package for caching PyTorch modules
Home-page: https://github.com/Littleor/torch-module-cache
Author: Littleor
Author-email: me@littleor.cn
License: MIT
Classifier: Programming Language :: Python :: 3
Classifier: License :: OSI Approved :: MIT License
Classifier: Operating System :: OS Independent
Requires-Python: >=3.6
License-File: LICENSE
Requires-Dist: torch>=1.7.0
Dynamic: author
Dynamic: author-email
Dynamic: classifier
Dynamic: description
Dynamic: description-content-type
Dynamic: home-page
Dynamic: license
Dynamic: license-file
Dynamic: requires-dist
Dynamic: requires-python
Dynamic: summary
